runner.py
battle_logger/__init__.py
battle_logger/calc.py
battle_logger/ocr_log_parser.py
battle_logger/op.py
battle_logger/pipeline.py
battle_logger/result.py
pokemon_go_video_analysis-0.0.0.0.5.5.dist-info/METADATA
pokemon_go_video_analysis-0.0.0.0.5.5.dist-info/WHEEL
pokemon_go_video_analysis-0.0.0.0.5.5.dist-info/licenses/LICENSE
pokemon_go_video_analysis-0.0.0.0.5.5.dist-info/RECORD
