Metadata-Version: 2.1
Name: pokemon-go-video-analysis
Version: 0.0.0.0.5.5
Summary: Pokemon Go Video Analysis
Project-URL: Homepage, https://github.com/prateekt/pokemon-go-video-analysis
Project-URL: Bug Tracker, https://github.com/prateekt/pokemon-go-video-analysis/issues
Author-email: Prateek Tandon <prateek1.tandon@gmail.com>
License-File: LICENSE
Classifier: License :: OSI Approved :: MIT License
Classifier: Operating System :: OS Independent
Classifier: Programming Language :: Python :: 3
Requires-Python: <=3.11.7
Requires-Dist: algo-ops
Requires-Dist: easyocr
Requires-Dist: pillow==9.5.0
Requires-Dist: pyspellchecker
Requires-Dist: pytesseract
Requires-Dist: shapely
